odoo/addons/sale_secondary_salesperson/README.rst
odoo/addons/sale_secondary_salesperson/__init__.py
odoo/addons/sale_secondary_salesperson/__manifest__.py
odoo/addons/sale_secondary_salesperson/i18n/ca.po
odoo/addons/sale_secondary_salesperson/i18n/es.po
odoo/addons/sale_secondary_salesperson/i18n/sale_secondary_salesperson.pot
odoo/addons/sale_secondary_salesperson/models/__init__.py
odoo/addons/sale_secondary_salesperson/models/sale_order.py
odoo/addons/sale_secondary_salesperson/readme/CONTRIBUTORS.rst
odoo/addons/sale_secondary_salesperson/readme/DESCRIPTION.rst
odoo/addons/sale_secondary_salesperson/readme/USAGE.rst
odoo/addons/sale_secondary_salesperson/report/__init__.py
odoo/addons/sale_secondary_salesperson/report/sale_report.py
odoo/addons/sale_secondary_salesperson/static/description/icon.png
odoo/addons/sale_secondary_salesperson/static/description/index.html
odoo/addons/sale_secondary_salesperson/tests/__init__.py
odoo/addons/sale_secondary_salesperson/tests/test_sale_order.py
odoo/addons/sale_secondary_salesperson/views/sale_order_view.xml
odoo12_addon_sale_secondary_salesperson-12.0.1.0.0.99.dev8.dist-info/METADATA
odoo12_addon_sale_secondary_salesperson-12.0.1.0.0.99.dev8.dist-info/WHEEL
odoo12_addon_sale_secondary_salesperson-12.0.1.0.0.99.dev8.dist-info/top_level.txt
odoo12_addon_sale_secondary_salesperson-12.0.1.0.0.99.dev8.dist-info/RECORD
